README.md
setup.py
my_ml_toolkit/__init__.py
my_ml_toolkit/models.py
my_ml_toolkit/preprocessing.py
my_ml_toolkit.egg-info/PKG-INFO
my_ml_toolkit.egg-info/SOURCES.txt
my_ml_toolkit.egg-info/dependency_links.txt
my_ml_toolkit.egg-info/requires.txt
my_ml_toolkit.egg-info/top_level.txt