Metadata-Version: 2.1
Name: my-ml-toolkit
Version: 0.1
Summary: A custom ML package with NumPy, Pandas, Scikit-learn, and SciPy.
Home-page: https://github.com/yourusername/my_ml_toolkit
Author: Your Name
Author-email: your_email@example.com
Classifier: Programming Language :: Python :: 3
Classifier: License :: OSI Approved :: MIT License
Classifier: Operating System :: OS Independent
Requires-Python: >=3.6
Requires-Dist: numpy
Requires-Dist: pandas
Requires-Dist: scikit-learn
Requires-Dist: scipy
